{"data":[{"id":6,"name":"Germany","country_code":"+49","currency_short_name":"€","curreny_standard_name":"EURO","country_time_zone":"UTC+2","country_topic":"Germany","distance_type":"Miles","country_ios_code":"ISO 3166-2:DE","is_show":true,"created_at":"2022-07-17T03:05:25.631Z","updated_at":"2022-07-17T03:11:15.000Z"},{"id":8,"name":"Italy","country_code":"+39","currency_short_name":"€","curreny_standard_name":"EURO","country_time_zone":"UTC+2","country_topic":"Italy","distance_type":"Miles","country_ios_code":"ISO 3166-2:IT","is_show":true,"created_at":"2022-07-17T03:13:59.580Z","updated_at":"2022-07-17T03:13:59.580Z"},{"id":1,"name":"Pakistan","country_code":"+92","currency_short_name":"Rs","curreny_standard_name":"PKR","country_time_zone":"Asia/Karachi","country_topic":"pakistan","distance_type":"Km","country_ios_code":"pk","is_show":true,"created_at":"2022-03-19T13:54:28.000Z","updated_at":"2022-04-25T20:54:37.638Z"},{"id":9,"name":"Switzerland","country_code":"+41","currency_short_name":"Fr","curreny_standard_name":"CHF Fr","country_time_zone":"UTC+2","country_topic":"Switzerland","distance_type":"Miles","country_ios_code":"ISO 3166-2:CH","is_show":true,"created_at":"2022-07-17T03:18:39.538Z","updated_at":"2022-07-17T03:18:39.538Z"},{"id":2,"name":"United Kingdom","country_code":"+44","currency_short_name":"£","curreny_standard_name":"GBP","country_time_zone":"Europe/London","country_topic":"united_kingdom","distance_type":"Miles","country_ios_code":"uk","is_show":true,"created_at":"2022-03-19T13:54:28.000Z","updated_at":"2022-04-25T20:54:37.638Z"}],"meta":{"total":5,"page":1,"last_page":1}}
